{
  "attempt": 1,
  "mode": "reground",
  "base_image": ".codepet/codepet.png",
  "candidate_image": ".codepet/new_pet.png",
  "checks": {
    "stage_identity": { "status": "pass", "evidence": "Byte is a teen blob with gangly limbs and appropriate proportions" },
    "pixel_style": { "status": "pass", "evidence": "Clean pixel art with dithered shading and readable silhouette" },
    "requested_changes_visible": { "status": "pass", "evidence": "Byte is sitting comfortably on the desk with evening lighting" },
    "artifact_free": { "status": "pass", "evidence": "No artifacts, text leakage, or malformed parts" },
    "anchors_present": { "status": "pass", "evidence": "Desk, oversized laptop, and Chicago skyline window are all visible" },
    "temporal_mood_match": { "status": "pass", "evidence": "Evening lighting matches time of day, Byte appears content" }
  },
  "decision": "accept"
}
